{"index_02_r_drv": [8, "E05", "FKIndexFinger2_R"], "index_metacarpal_l_drv": [8, "E04", "ctl_index_metacarpal_l_001"], "jnt_ankleIk_l_001": [12, "C01", "IKLeg_L"], "upperarm_r_drv": [15, "D00", "FKShoulder_R"], "ring_metacarpal_l_drv": [8, "E04", "ctl_ring_metacarpal_l_001"], "ring_03_l_drv": [8, "E05", "FKRingFinger3_L"], "index_03_r_drv": [8, "E05", "FKIndexFinger3_R"], "neck_01_drv": [25, "D05", "FKNeck_M"], "thumb_01_l_drv": [8, "E04", "FKThumbFinger1_L"], "pinky_03_l_drv": [8, "E05", "FKPinkyFinger3_L"], "middle_03_l_drv": [8, "E05", "FKMiddleFinger3_L"], "lowerarm_l_drv": [15, "D00", "FKElbow_L"], "middle_metacarpal_r_drv": [8, "E04", "ctl_middle_metacarpal_r_001"], "jnt_ballIk_l_001": [11, "D05", "IKToes_L"], "hand_r_drv": [10, "D00", "FKWrist_R"], "middle_metacarpal_l_drv": [8, "E04", "ctl_middle_metacarpal_l_001"], "ring_02_l_drv": [8, "E05", "FKRingFinger2_L"], "spine_05_drv": [40, "D00", "FKChest_M"], "jnt_WristIk_r_001": [20, "Z03", "IKArm_R"], "pinky_01_l_drv": [8, "E05", "FKPinkyFinger1_L"], "foot_r_drv": [20, "D00", "FKAnkle_R"], "thumb_01_r_drv": [8, "E04", "FKThumbFinger1_R"], "middle_03_r_drv": [8, "E05", "FKMiddleFinger3_R"], "index_03_l_drv": [8, "E05", "FKIndexFinger3_L"], "middle_01_l_drv": [8, "E05", "FKMiddleFinger1_L"], "index_01_l_drv": [8, "E05", "FKIndexFinger1_L"], "ball_r_drv": [10, "D00", "FKToes_R"], "clavicle_l_drv": [35, "D12", "FKScapula_L"], "pelvis_drv": [40, "D00", "FKRoot_M"], "jnt_WristIk_l_001": [20, "Z03", "IKArm_L"], "pinky_metacarpal_l_drv": [8, "E04", "FKCup_L"], "pinky_03_r_drv": [8, "E05", "FKPinkyFinger3_R"], "jnt_ankleIk_r_001": [12, "C01", "IKLeg_R"], "pinky_02_l_drv": [8, "E05", "FKPinkyFinger2_L"], "middle_02_r_drv": [8, "E05", "FKMiddleFinger2_R"], "ring_01_l_drv": [8, "E05", "FKRingFinger1_L"], "jnt_ballIk_r_001": [11, "D05", "IKToes_R"], "ball_l_drv": [10, "D00", "FKToes_L"], "thumb_03_l_drv": [8, "E05", "FKThumbFinger3_L"], "index_02_l_drv": [8, "E05", "FKIndexFinger2_L"], "clavicle_r_drv": [35, "D12", "FKScapula_R"], "ring_metacarpal_r_drv": [8, "E04", "ctl_ring_metacarpal_r_001"], "ring_03_r_drv": [8, "E05", "FKRingFinger3_R"], "middle_01_r_drv": [8, "E05", "FKMiddleFinger1_R"], "head_drv": [25, "F00", "FKHead_M"], "thumb_02_l_drv": [8, "E05", "FKThumbFinger2_L"], "calf_l_drv": [20, "D00", "FKKnee_L"], "index_metacarpal_r_drv": [8, "E04", "ctl_index_metacarpal_r_001"], "ring_01_r_drv": [8, "E05", "FKRingFinger1_R"], "pinky_metacarpal_r_drv": [8, "E04", "FKCup_R"], "pinky_01_r_drv": [8, "E05", "FKPinkyFinger1_R"], "thigh_l_drv": [20, "D00", "FKHip_L"], "index_01_r_drv": [8, "E05", "FKIndexFinger1_R"], "thumb_03_r_drv": [8, "E05", "FKThumbFinger3_R"], "thigh_r_drv": [20, "D00", "FKHip_R"], "spine_03_drv": [40, "D00", "FKSpine1_M"], "ring_02_r_drv": [8, "E05", "FKRingFinger2_R"], "thumb_02_r_drv": [8, "E05", "FKThumbFinger2_R"], "pinky_02_r_drv": [8, "E05", "FKPinkyFinger2_R"], "middle_02_l_drv": [8, "E05", "FKMiddleFinger2_L"], "calf_r_drv": [20, "D00", "FKKnee_R"], "upperarm_l_drv": [15, "D00", "FKShoulder_L"], "hand_l_drv": [10, "D00", "FKWrist_L"], "foot_l_drv": [20, "D00", "FKAnkle_L"], "lowerarm_r_drv": [15, "D00", "FKElbow_R"]}